[
  1,
  0,
  0,
  [
    [
      "dragonBones.DragonBonesAsset",
      [
        "_name",
        "_dragonBonesJson"
      ],
      1
    ]
  ],
  [
    [
      0,
      0,
      1,
      3
    ]
  ],
  [
    [
      0,
      "strike_ef_ske",
      "{\"frameRate\":25,\"name\":\"strike_ef\",\"version\":\"5.5\",\"compatibleVersion\":\"5.5\",\"armature\":[{\"type\":\"Armature\",\"frameRate\":25,\"name\":\"strike_ef\",\"aabb\":{\"x\":-37.45,\"y\":-38.15,\"width\":80,\"height\":81},\"bone\":[{\"name\":\"root\"},{\"inheritScale\":false,\"name\":\"图层 9\",\"parent\":\"root\",\"transform\":{\"x\":4.8,\"y\":6,\"scX\":2.01,\"scY\":2.01}},{\"inheritScale\":false,\"name\":\"图层 13\",\"parent\":\"root\",\"transform\":{\"x\":2.5,\"y\":4.35}},{\"inheritScale\":false,\"name\":\"图层 2\",\"parent\":\"root\",\"transform\":{\"x\":-0.15,\"y\":-0.45,\"scX\":0.54,\"scY\":0.54}}],\"slot\":[{\"blendMode\":\"add\",\"name\":\"图层 2\",\"parent\":\"图层 2\",\"color\":{\"rM\":5,\"gM\":79,\"bM\":82}},{\"blendMode\":\"add\",\"name\":\"图层 13\",\"parent\":\"图层 13\"},{\"blendMode\":\"add\",\"name\":\"图层 9\",\"parent\":\"图层 9\"}],\"skin\":[{\"slot\":[{\"name\":\"图层 13\",\"display\":[{\"name\":\"shanke.cn_1_15_97034\",\"transform\":{\"x\":0.05,\"y\":-2}}]},{\"name\":\"图层 2\",\"display\":[{\"name\":\"dsggg\",\"transform\":{\"x\":0.25,\"y\":0.2,\"skX\":-0.01,\"skY\":-0.01}}]},{\"name\":\"图层 9\",\"display\":[{\"name\":\"fhh\",\"transform\":{\"x\":0.1,\"y\":0.1}}]}]}],\"animation\":[{\"duration\":9,\"fadeInTime\":0.3,\"name\":\"start\",\"bone\":[{\"name\":\"图层 2\",\"scaleFrame\":[{\"duration\":3,\"tweenEasing\":0},{\"duration\":3,\"tweenEasing\":0,\"x\":2.44,\"y\":2.44},{\"duration\":3,\"x\":2.8,\"y\":2.8}]},{\"name\":\"图层 13\",\"scaleFrame\":[{\"duration\":2,\"tweenEasing\":0},{\"duration\":7,\"tweenEasing\":0,\"x\":1.88,\"y\":1.88},{\"duration\":0,\"x\":2.5,\"y\":2.5}]},{\"name\":\"图层 9\",\"translateFrame\":[{\"tweenEasing\":0},{\"duration\":5,\"tweenEasing\":0,\"x\":2.6,\"y\":2.6},{\"duration\":3,\"x\":3.6,\"y\":3.6}],\"scaleFrame\":[{\"tweenEasing\":0},{\"duration\":5,\"tweenEasing\":0,\"x\":1.73,\"y\":1.73},{\"duration\":3,\"x\":1.98,\"y\":1.98}]}],\"slot\":[{\"name\":\"图层 2\",\"colorFrame\":[{\"duration\":3,\"tweenEasing\":0},{\"duration\":3,\"tweenEasing\":0},{\"duration\":3,\"value\":{\"aM\":0}}]},{\"name\":\"图层 13\",\"colorFrame\":[{\"duration\":2,\"tweenEasing\":0},{\"duration\":7,\"tweenEasing\":0},{\"duration\":0,\"value\":{\"aM\":0}}]},{\"name\":\"图层 9\",\"colorFrame\":[{\"tweenEasing\":0},{\"duration\":5,\"tweenEasing\":0},{\"duration\":3,\"value\":{\"aM\":0}}]}]}],\"defaultActions\":[{\"gotoAndPlay\":\"start\"}]}]}"
    ]
  ],
  0,
  0,
  [],
  [],
  []
]