[
  1,
  [
    "edz8zzlwlE9Io2GyriJ9I6"
  ],
  [
    "_texture"
  ],
  [
    [
      "dragonBones.DragonBonesAtlasAsset",
      [
        "_name",
        "_atlasJson"
      ],
      1
    ]
  ],
  [
    [
      0,
      0,
      1,
      3
    ]
  ],
  [
    [
      0,
      "ef_hhe_huojianqiang_tex",
      "{\"SubTexture\":[{\"y\":226,\"frameX\":0,\"frameY\":-1,\"width\":26,\"frameWidth\":27,\"height\":29,\"name\":\"元件 1 复制\",\"frameHeight\":30,\"x\":1},{\"y\":1,\"frameX\":-3,\"frameY\":-3,\"width\":61,\"frameWidth\":70,\"height\":76,\"name\":\"元件 26\",\"frameHeight\":80,\"x\":376},{\"y\":1,\"frameX\":-5,\"frameY\":-5,\"width\":63,\"frameWidth\":70,\"height\":73,\"name\":\"元件 24\",\"frameHeight\":80,\"x\":439},{\"y\":76,\"frameX\":-2,\"frameY\":-4,\"width\":62,\"frameWidth\":70,\"height\":74,\"name\":\"元件 25\",\"frameHeight\":80,\"x\":439},{\"y\":79,\"frameX\":-6,\"frameY\":-9,\"width\":59,\"frameWidth\":70,\"height\":69,\"name\":\"元件 28\",\"frameHeight\":80,\"x\":376},{\"y\":152,\"frameX\":-1,\"frameY\":-6,\"width\":62,\"frameWidth\":70,\"height\":72,\"name\":\"元件 27\",\"frameHeight\":80,\"x\":1},{\"y\":1,\"frameX\":0,\"frameY\":-1,\"width\":285,\"frameWidth\":285,\"height\":59,\"name\":\"元件 35\",\"frameHeight\":60,\"x\":1},{\"y\":1,\"frameX\":-1,\"frameY\":-4,\"width\":86,\"frameWidth\":89,\"height\":84,\"name\":\"元件 34 复制 2\",\"frameHeight\":89,\"x\":288},{\"width\":17,\"y\":226,\"height\":17,\"name\":\"元件 57f\",\"x\":29}],\"width\":512,\"height\":256,\"name\":\"ef_hhe_huojianqiang\",\"imagePath\":\"ef_hhe_huojianqiang_tex.png\"}"
    ]
  ],
  0,
  0,
  [
    0
  ],
  [
    0
  ],
  [
    0
  ]
]