[
  1,
  [
    "3fi3WzRkxImJhMa7kqzgOQ"
  ],
  [
    "_texture"
  ],
  [
    [
      "dragonBones.DragonBonesAtlasAsset",
      [
        "_name",
        "_atlasJson"
      ],
      1
    ],
    [
      "dragonBones.DragonBonesAsset",
      [
        "_name",
        "_dragonBonesJson"
      ],
      1
    ]
  ],
  [
    [
      0,
      0,
      1,
      3
    ],
    [
      1,
      0,
      1,
      3
    ]
  ],
  [
    [
      [
        [
          0,
          "ef_jinggubang_tex",
          "{\"width\":128,\"imagePath\":\"ef_jinggubang_4_tex.png\",\"height\":256,\"name\":\"ef_jinggubang_4\",\"SubTexture\":[{\"frameHeight\":34,\"y\":1,\"frameX\":-2,\"width\":124,\"frameY\":-2,\"height\":26,\"name\":\"cn_1_16_79375\",\"frameWidth\":132,\"x\":1},{\"frameHeight\":64,\"y\":61,\"frameX\":-4,\"width\":43,\"frameY\":-2,\"height\":52,\"name\":\"cn_1_14_96312\",\"frameWidth\":51,\"x\":83},{\"frameHeight\":42,\"y\":115,\"frameX\":-3,\"width\":44,\"frameY\":-5,\"height\":32,\"name\":\"cn_1_15_67358\",\"frameWidth\":54,\"x\":41},{\"frameHeight\":50,\"y\":91,\"frameX\":-5,\"width\":38,\"frameY\":-2,\"height\":45,\"name\":\"cn_1_12_16659\",\"frameWidth\":48,\"x\":1},{\"frameHeight\":14,\"y\":91,\"frameX\":-1,\"width\":11,\"frameY\":0,\"height\":11,\"name\":\"cn_1_3_40705\",\"frameWidth\":14,\"x\":67},{\"frameHeight\":17,\"y\":91,\"frameX\":-2,\"width\":24,\"frameY\":-1,\"height\":13,\"name\":\"cn_1_10_79484\",\"frameWidth\":31,\"x\":41},{\"frameHeight\":38,\"y\":29,\"frameX\":-2,\"width\":90,\"frameY\":-2,\"height\":30,\"name\":\"cn_1_4_14125\",\"frameWidth\":96,\"x\":1},{\"frameHeight\":34,\"y\":61,\"frameX\":-2,\"width\":80,\"frameY\":-2,\"height\":28,\"name\":\"cn_1_7_25273\",\"frameWidth\":87,\"x\":1}]}"
        ]
      ],
      0,
      0,
      [
        0
      ],
      [
        0
      ],
      [
        0
      ]
    ],
    [
      [
        [
          1,
          "ef_jinggubang_ske",
          "{\"frameRate\":25,\"name\":\"ef_jinggubang_4\",\"version\":\"5.5\",\"compatibleVersion\":\"5.5\",\"armature\":[{\"type\":\"Armature\",\"frameRate\":25,\"name\":\"jingubang\",\"aabb\":{\"x\":-7,\"y\":-66.54,\"width\":144.46,\"height\":127.31},\"bone\":[{\"name\":\"root\"},{\"inheritScale\":false,\"name\":\"图层_10\",\"parent\":\"root\",\"transform\":{\"x\":83.9,\"y\":-6.1,\"scX\":0.7,\"scY\":0.7}},{\"inheritScale\":false,\"name\":\"图层 6\",\"parent\":\"root\",\"transform\":{\"x\":98,\"y\":-48.4,\"skX\":70.18,\"skY\":70.18,\"scX\":1.74}},{\"inheritScale\":false,\"name\":\"图层 5\",\"parent\":\"root\",\"transform\":{\"x\":78.9,\"y\":19.25,\"skX\":4.56,\"skY\":4.56,\"scX\":0.86}},{\"inheritScale\":false,\"name\":\"图层 4\",\"parent\":\"root\",\"transform\":{\"x\":88.6,\"y\":43,\"skX\":-47.14,\"skY\":-47.14,\"scX\":1.83}},{\"inheritScale\":false,\"name\":\"图层 3\",\"parent\":\"root\",\"transform\":{\"x\":111.7,\"y\":37.75,\"skX\":-53.68,\"skY\":-53.68,\"scX\":1.2}},{\"inheritScale\":false,\"name\":\"图层 13\",\"parent\":\"root\",\"transform\":{\"x\":108.55,\"y\":-21.5,\"skX\":-66.97,\"skY\":-66.97}},{\"inheritScale\":false,\"name\":\"图层 12\",\"parent\":\"root\",\"transform\":{\"x\":103.2,\"y\":19.6,\"skX\":27.02,\"skY\":27.02}},{\"inheritScale\":false,\"name\":\"图层_12\",\"parent\":\"root\",\"transform\":{\"x\":91.2,\"y\":-12.75,\"scX\":0.72,\"scY\":0.72}},{\"inheritScale\":false,\"name\":\"图层_11\",\"parent\":\"root\",\"transform\":{\"x\":82.7,\"y\":10.25,\"scX\":0.5,\"scY\":0.5}},{\"inheritScale\":false,\"name\":\"图层 7\",\"parent\":\"root\",\"transform\":{\"x\":103,\"y\":4.8,\"skX\":43.19,\"skY\":43.19}},{\"inheritScale\":false,\"name\":\"图层_9\",\"parent\":\"root\",\"transform\":{\"x\":87.6,\"y\":1.1,\"scX\":0.54,\"scY\":0.54}},{\"inheritScale\":false,\"name\":\"图层_8\",\"parent\":\"root\",\"transform\":{\"x\":93.95,\"y\":12.45,\"scX\":0.75,\"scY\":0.75}},{\"inheritScale\":false,\"name\":\"图层_3\",\"parent\":\"root\",\"transform\":{\"x\":85.85,\"y\":-16.4}},{\"inheritScale\":false,\"name\":\"图层_7\",\"parent\":\"root\",\"transform\":{\"x\":78.5,\"y\":-12.2,\"scX\":0.5,\"scY\":0.5}},{\"inheritScale\":false,\"name\":\"图层_4\",\"parent\":\"root\",\"transform\":{\"x\":77.8,\"y\":-4.2,\"scX\":0.7,\"scY\":0.7}},{\"inheritScale\":false,\"name\":\"图层_5\",\"parent\":\"root\",\"transform\":{\"x\":85.4,\"y\":2.5,\"scX\":0.54,\"scY\":0.54}},{\"inheritScale\":false,\"name\":\"图层_6\",\"parent\":\"root\",\"transform\":{\"x\":87.7,\"y\":16.85,\"scX\":0.75,\"scY\":0.75}},{\"inheritScale\":false,\"name\":\"图层_2\",\"parent\":\"root\",\"transform\":{\"x\":117.25,\"y\":-0.35}},{\"inheritScale\":false,\"name\":\"图层_1\",\"parent\":\"root\",\"transform\":{\"x\":57.1,\"y\":-0.05}}],\"slot\":[{\"name\":\"图层_1\",\"parent\":\"图层_1\"},{\"name\":\"图层 12\",\"parent\":\"图层 12\"},{\"name\":\"图层 13\",\"parent\":\"图层 13\"},{\"name\":\"图层_2\",\"parent\":\"图层_2\"},{\"name\":\"图层_6\",\"parent\":\"图层_6\"},{\"name\":\"图层_5\",\"parent\":\"图层_5\"},{\"name\":\"图层_4\",\"parent\":\"图层_4\"},{\"name\":\"图层_7\",\"parent\":\"图层_7\"},{\"name\":\"图层_3\",\"parent\":\"图层_3\"},{\"name\":\"图层_8\",\"parent\":\"图层_8\"},{\"name\":\"图层_9\",\"parent\":\"图层_9\"},{\"name\":\"图层_10\",\"parent\":\"图层_10\"},{\"name\":\"图层_11\",\"parent\":\"图层_11\"},{\"name\":\"图层_12\",\"parent\":\"图层_12\"},{\"name\":\"图层 3\",\"parent\":\"图层 3\"},{\"name\":\"图层 4\",\"parent\":\"图层 4\"},{\"name\":\"图层 5\",\"parent\":\"图层 5\"},{\"name\":\"图层 6\",\"parent\":\"图层 6\"},{\"name\":\"图层 7\",\"parent\":\"图层 7\"}],\"skin\":[{\"slot\":[{\"name\":\"图层_10\",\"display\":[{\"name\":\"cn_1_3_40705\",\"transform\":{\"x\":0.95,\"y\":1.2}}]},{\"name\":\"图层_6\",\"display\":[{\"name\":\"cn_1_3_40705\",\"transform\":{\"x\":1.05,\"y\":1.1}}]},{\"name\":\"图层 5\",\"display\":[{\"name\":\"cn_1_10_79484\",\"transform\":{\"x\":-6.3,\"y\":1.2}}]},{\"name\":\"图层_11\",\"display\":[{\"name\":\"cn_1_3_40705\",\"transform\":{\"x\":0.75,\"y\":1.25}}]},{\"name\":\"图层 6\",\"display\":[{\"name\":\"cn_1_10_79484\",\"transform\":{\"x\":-6.2,\"y\":1.5}}]},{\"name\":\"图层_9\",\"display\":[{\"name\":\"cn_1_3_40705\",\"transform\":{\"x\":0.85,\"y\":1.25}}]},{\"name\":\"图层_4\",\"display\":[{\"name\":\"cn_1_3_40705\",\"transform\":{\"x\":0.95,\"y\":1.25}}]},{\"name\":\"图层_3\",\"display\":[{\"name\":\"cn_1_3_40705\",\"transform\":{\"x\":1.05,\"y\":1.15}}]},{\"name\":\"图层_2\",\"display\":[{\"name\":\"cn_1_12_16659\",\"transform\":{\"x\":-16.45,\"y\":0.35}}]},{\"name\":\"图层 3\",\"display\":[{\"name\":\"cn_1_10_79484\",\"transform\":{\"x\":-6.3,\"y\":1.4}}]},{\"name\":\"图层 7\",\"display\":[{\"name\":\"cn_1_4_14125\",\"transform\":{\"x\":-34.55,\"y\":-4.35}},{\"name\":\"cn_1_7_25273\",\"transform\":{\"x\":1.75,\"y\":1.1}}]},{\"name\":\"图层_12\",\"display\":[{\"name\":\"cn_1_3_40705\",\"transform\":{\"x\":1.05,\"y\":1.15}}]},{\"name\":\"图层 13\",\"display\":[{\"name\":\"cn_1_15_67358\",\"transform\":{\"x\":1.7,\"y\":1.35}}]},{\"name\":\"图层 12\",\"display\":[{\"name\":\"cn_1_14_96312\",\"transform\":{\"x\":1.5,\"y\":1.5}}]},{\"name\":\"图层_1\",\"display\":[{\"name\":\"cn_1_16_79375\",\"transform\":{\"x\":1.9,\"y\":2}}]},{\"name\":\"图层_7\",\"display\":[{\"name\":\"cn_1_3_40705\",\"transform\":{\"x\":0.75,\"y\":1.25}}]},{\"name\":\"图层_8\",\"display\":[{\"name\":\"cn_1_3_40705\",\"transform\":{\"x\":1.05,\"y\":1.1}}]},{\"name\":\"图层 4\",\"display\":[{\"name\":\"cn_1_10_79484\",\"transform\":{\"x\":-6.35,\"y\":1.1}}]},{\"name\":\"图层_5\",\"display\":[{\"name\":\"cn_1_3_40705\",\"transform\":{\"x\":0.85,\"y\":1.25}}]}]}],\"animation\":[{\"duration\":6,\"playTimes\":0,\"fadeInTime\":0.3,\"name\":\"start\",\"bone\":[{\"name\":\"图层_2\",\"translateFrame\":[{\"duration\":2,\"tweenEasing\":0},{\"duration\":2,\"tweenEasing\":0,\"x\":0.2},{\"duration\":2,\"tweenEasing\":0},{\"duration\":0,\"x\":0.2}],\"scaleFrame\":[{\"duration\":2,\"tweenEasing\":0},{\"duration\":2,\"tweenEasing\":0,\"x\":0.76},{\"duration\":2,\"tweenEasing\":0},{\"duration\":0,\"x\":0.76}]},{\"name\":\"图层_6\",\"translateFrame\":[{\"duration\":3,\"tweenEasing\":0},{\"duration\":3,\"x\":-29.3,\"y\":-0.3}],\"scaleFrame\":[{\"duration\":3,\"tweenEasing\":0},{\"duration\":3,\"x\":0.48,\"y\":0.48}]},{\"name\":\"图层_5\",\"translateFrame\":[{\"duration\":3,\"tweenEasing\":0},{\"duration\":3,\"x\":-28.6,\"y\":0.35}],\"scaleFrame\":[{\"duration\":3,\"tweenEasing\":0},{\"duration\":3,\"x\":0.39,\"y\":0.39}]},{\"name\":\"图层_4\",\"translateFrame\":[{\"duration\":3,\"tweenEasing\":0},{\"duration\":3,\"x\":-31.4,\"y\":0.4}],\"scaleFrame\":[{\"duration\":3,\"tweenEasing\":0},{\"duration\":3,\"x\":0.54,\"y\":0.54}]},{\"name\":\"图层_7\",\"translateFrame\":[{\"duration\":3,\"tweenEasing\":0},{\"duration\":3,\"x\":-31.4,\"y\":-2.4}],\"scaleFrame\":[{\"duration\":3,\"tweenEasing\":0},{\"duration\":3,\"x\":0.76,\"y\":0.76}]},{\"name\":\"图层_3\",\"translateFrame\":[{\"duration\":3,\"tweenEasing\":0},{\"duration\":3,\"x\":-26.05,\"y\":-2.4}],\"scaleFrame\":[{\"duration\":3,\"tweenEasing\":0},{\"duration\":3,\"x\":0.32,\"y\":0.32}]},{\"name\":\"图层_8\",\"translateFrame\":[{\"duration\":2,\"tweenEasing\":0},{\"duration\":4,\"tweenEasing\":0},{\"duration\":0,\"x\":-35.55,\"y\":4.1}],\"scaleFrame\":[{\"duration\":2,\"tweenEasing\":0},{\"duration\":4,\"tweenEasing\":0},{\"duration\":0,\"x\":0.48,\"y\":0.48}]},{\"name\":\"图层_9\",\"translateFrame\":[{\"duration\":2,\"tweenEasing\":0},{\"duration\":4,\"tweenEasing\":0},{\"duration\":0,\"x\":-30.8,\"y\":1.75}],\"scaleFrame\":[{\"duration\":2,\"tweenEasing\":0},{\"duration\":4,\"tweenEasing\":0},{\"duration\":0,\"x\":0.39,\"y\":0.39}]},{\"name\":\"图层_10\",\"translateFrame\":[{\"duration\":2,\"tweenEasing\":0},{\"duration\":4,\"tweenEasing\":0},{\"duration\":0,\"x\":-37.5,\"y\":2.3}],\"scaleFrame\":[{\"duration\":2,\"tweenEasing\":0},{\"duration\":4,\"tweenEasing\":0},{\"duration\":0,\"x\":0.54,\"y\":0.54}]},{\"name\":\"图层_11\",\"translateFrame\":[{\"duration\":2,\"tweenEasing\":0},{\"duration\":4,\"tweenEasing\":0},{\"duration\":0,\"x\":-35.6,\"y\":-24.85}],\"scaleFrame\":[{\"duration\":2,\"tweenEasing\":0},{\"duration\":4,\"tweenEasing\":0},{\"duration\":0,\"x\":0.76,\"y\":0.76}]},{\"name\":\"图层_12\",\"translateFrame\":[{\"duration\":2,\"tweenEasing\":0},{\"duration\":4,\"tweenEasing\":0},{\"duration\":0,\"x\":-31.4,\"y\":-6.05}],\"scaleFrame\":[{\"duration\":2,\"tweenEasing\":0},{\"duration\":4,\"tweenEasing\":0},{\"duration\":0,\"x\":0.44,\"y\":0.44}]}],\"slot\":[{\"name\":\"图层_6\",\"colorFrame\":[{\"duration\":3,\"tweenEasing\":0},{\"tweenEasing\":0},{\"duration\":2,\"value\":{\"aM\":0}}]},{\"name\":\"图层_5\",\"colorFrame\":[{\"duration\":3,\"tweenEasing\":0},{\"tweenEasing\":0},{\"duration\":2,\"value\":{\"aM\":0}}]},{\"name\":\"图层_4\",\"colorFrame\":[{\"duration\":3,\"tweenEasing\":0},{\"tweenEasing\":0},{\"duration\":2,\"value\":{\"aM\":0}}]},{\"name\":\"图层_7\",\"colorFrame\":[{\"duration\":3,\"tweenEasing\":0},{\"tweenEasing\":0},{\"duration\":2,\"value\":{\"aM\":0}}]},{\"name\":\"图层_3\",\"colorFrame\":[{\"duration\":3,\"tweenEasing\":0},{\"tweenEasing\":0},{\"duration\":2,\"value\":{\"aM\":0}}]},{\"name\":\"图层_8\",\"colorFrame\":[{\"tweenEasing\":0,\"value\":{\"aM\":0}},{\"tweenEasing\":0,\"value\":{\"aM\":0}},{\"duration\":4}]},{\"name\":\"图层_9\",\"colorFrame\":[{\"tweenEasing\":0,\"value\":{\"aM\":0}},{\"tweenEasing\":0,\"value\":{\"aM\":0}},{\"duration\":4}]},{\"name\":\"图层_10\",\"colorFrame\":[{\"tweenEasing\":0,\"value\":{\"aM\":0}},{\"tweenEasing\":0,\"value\":{\"aM\":0}},{\"duration\":4}]},{\"name\":\"图层_11\",\"colorFrame\":[{\"tweenEasing\":0,\"value\":{\"aM\":0}},{\"tweenEasing\":0,\"value\":{\"aM\":0}},{\"duration\":4}]},{\"name\":\"图层_12\",\"colorFrame\":[{\"tweenEasing\":0,\"value\":{\"aM\":0}},{\"tweenEasing\":0,\"value\":{\"aM\":0}},{\"duration\":4}]},{\"name\":\"图层 12\",\"displayFrame\":[{\"duration\":6,\"value\":-1}]},{\"name\":\"图层 13\",\"displayFrame\":[{\"duration\":6,\"value\":-1}]},{\"name\":\"图层 3\",\"displayFrame\":[{\"duration\":6,\"value\":-1}]},{\"name\":\"图层 4\",\"displayFrame\":[{\"duration\":6,\"value\":-1}]},{\"name\":\"图层 5\",\"displayFrame\":[{\"duration\":6,\"value\":-1}]},{\"name\":\"图层 6\",\"displayFrame\":[{\"duration\":6,\"value\":-1}]},{\"name\":\"图层 7\",\"displayFrame\":[{\"duration\":6,\"value\":-1}]}]},{\"duration\":13,\"fadeInTime\":0.3,\"name\":\"end\",\"bone\":[{\"name\":\"图层_1\",\"translateFrame\":[{\"tweenEasing\":0},{\"tweenEasing\":0,\"x\":57.05},{\"duration\":11}],\"scaleFrame\":[{\"tweenEasing\":0},{\"tweenEasing\":0,\"x\":0.68,\"y\":1.17},{\"duration\":11}]},{\"name\":\"图层_2\",\"translateFrame\":[{\"duration\":13,\"x\":0.2}],\"scaleFrame\":[{\"duration\":13,\"x\":0.76}]},{\"name\":\"图层 3\",\"translateFrame\":[{\"tweenEasing\":0,\"x\":-111.7,\"y\":-37.75},{\"tweenEasing\":0},{\"duration\":3,\"tweenEasing\":0},{\"duration\":8,\"x\":-15.75,\"y\":29.5}],\"rotateFrame\":[{\"tweenEasing\":0,\"rotate\":53.68},{\"tweenEasing\":0},{\"duration\":3,\"tweenEasing\":0},{\"duration\":8,\"rotate\":-0.06}],\"scaleFrame\":[{\"tweenEasing\":0,\"x\":0.83},{\"tweenEasing\":0},{\"duration\":3,\"tweenEasing\":0},{\"duration\":8,\"x\":0.23,\"y\":0.43}]},{\"name\":\"图层 4\",\"translateFrame\":[{\"tweenEasing\":0,\"x\":-88.6,\"y\":-43},{\"tweenEasing\":0},{\"duration\":3,\"tweenEasing\":0},{\"duration\":8,\"x\":-32.05,\"y\":38.8}],\"rotateFrame\":[{\"tweenEasing\":0,\"rotate\":47.14},{\"tweenEasing\":0},{\"duration\":3,\"tweenEasing\":0},{\"duration\":8,\"rotate\":-0.01}],\"scaleFrame\":[{\"tweenEasing\":0,\"x\":0.55},{\"tweenEasing\":0},{\"duration\":3,\"tweenEasing\":0},{\"duration\":8,\"x\":0.16,\"y\":0.36}]},{\"name\":\"图层 5\",\"translateFrame\":[{\"tweenEasing\":0,\"x\":-78.9,\"y\":-19.25},{\"tweenEasing\":0},{\"duration\":3,\"tweenEasing\":0},{\"duration\":8,\"x\":-33.35}],\"rotateFrame\":[{\"tweenEasing\":0,\"rotate\":-4.56},{\"tweenEasing\":0},{\"duration\":3,\"tweenEasing\":0},{\"duration\":8,\"rotate\":0.19}],\"scaleFrame\":[{\"tweenEasing\":0,\"x\":1.16},{\"tweenEasing\":0},{\"duration\":3,\"tweenEasing\":0},{\"duration\":8,\"x\":0.26,\"y\":0.49}]},{\"name\":\"图层 6\",\"translateFrame\":[{\"tweenEasing\":0,\"x\":-98,\"y\":48.4},{\"tweenEasing\":0},{\"duration\":3,\"tweenEasing\":0},{\"duration\":8,\"x\":-16.5,\"y\":-43.6}],\"rotateFrame\":[{\"tweenEasing\":0,\"rotate\":-70.18},{\"tweenEasing\":0},{\"duration\":3,\"tweenEasing\":0},{\"duration\":8,\"rotate\":-0.11}],\"scaleFrame\":[{\"tweenEasing\":0,\"x\":0.57},{\"tweenEasing\":0},{\"duration\":3,\"tweenEasing\":0},{\"duration\":8,\"x\":0.2,\"y\":0.47}]},{\"name\":\"图层 7\",\"translateFrame\":[{\"tweenEasing\":0,\"x\":-103,\"y\":-4.8},{\"tweenEasing\":0},{\"duration\":2,\"tweenEasing\":0},{\"duration\":2,\"tweenEasing\":0,\"x\":-71.25,\"y\":-21.65},{\"tweenEasing\":0,\"x\":-61.05,\"y\":-53.9},{\"tweenEasing\":0,\"x\":-100.15,\"y\":-28.6},{\"tweenEasing\":0,\"x\":-92.15,\"y\":-39.7},{\"duration\":2,\"tweenEasing\":0,\"x\":-118.95,\"y\":-80.05},{\"duration\":2,\"x\":-153.8,\"y\":-46.9}],\"rotateFrame\":[{\"tweenEasing\":0,\"rotate\":-43.19},{\"tweenEasing\":0},{\"duration\":2,\"tweenEasing\":0},{\"duration\":2,\"tweenEasing\":0,\"rotate\":111.68},{\"tweenEasing\":0,\"rotate\":-26},{\"tweenEasing\":0,\"rotate\":75.46},{\"tweenEasing\":0,\"rotate\":-6.2},{\"duration\":2,\"tweenEasing\":0,\"rotate\":-74.7},{\"duration\":2,\"rotate\":75.46}],\"scaleFrame\":[{\"duration\":2,\"tweenEasing\":0},{\"duration\":2,\"tweenEasing\":0},{\"duration\":2,\"tweenEasing\":0,\"x\":1.07},{\"tweenEasing\":0,\"x\":1.43,\"y\":1.43},{\"tweenEasing\":0,\"x\":1.02,\"y\":1.12},{\"tweenEasing\":0,\"x\":1.12,\"y\":1.25},{\"duration\":2,\"tweenEasing\":0,\"x\":1.45,\"y\":1.45},{\"duration\":2,\"x\":1.1,\"y\":1.21}]}],\"slot\":[{\"name\":\"图层_1\",\"colorFrame\":[{\"tweenEasing\":0},{\"tweenEasing\":0},{\"duration\":11,\"value\":{\"aM\":0}}]},{\"name\":\"图层 12\",\"colorFrame\":[{\"tweenEasing\":0,\"value\":{\"aM\":0}},{\"tweenEasing\":0},{\"duration\":11,\"value\":{\"aM\":0}}]},{\"name\":\"图层 13\",\"colorFrame\":[{\"tweenEasing\":0,\"value\":{\"aM\":0}},{\"tweenEasing\":0},{\"duration\":11,\"value\":{\"aM\":0}}]},{\"name\":\"图层_2\",\"colorFrame\":[{\"tweenEasing\":0},{\"duration\":12,\"value\":{\"aM\":0}}]},{\"name\":\"图层_6\",\"colorFrame\":[{\"duration\":13,\"value\":{\"aM\":0}}]},{\"name\":\"图层_5\",\"colorFrame\":[{\"duration\":13,\"value\":{\"aM\":0}}]},{\"name\":\"图层_4\",\"colorFrame\":[{\"duration\":13,\"value\":{\"aM\":0}}]},{\"name\":\"图层_7\",\"colorFrame\":[{\"duration\":13,\"value\":{\"aM\":0}}]},{\"name\":\"图层_3\",\"colorFrame\":[{\"duration\":13,\"value\":{\"aM\":0}}]},{\"name\":\"图层_8\",\"colorFrame\":[{\"duration\":13,\"value\":{\"aM\":0}}]},{\"name\":\"图层_9\",\"colorFrame\":[{\"duration\":13,\"value\":{\"aM\":0}}]},{\"name\":\"图层_10\",\"colorFrame\":[{\"duration\":13,\"value\":{\"aM\":0}}]},{\"name\":\"图层_11\",\"colorFrame\":[{\"duration\":13,\"value\":{\"aM\":0}}]},{\"name\":\"图层_12\",\"colorFrame\":[{\"duration\":13,\"value\":{\"aM\":0}}]},{\"name\":\"图层 3\",\"displayFrame\":[{\"value\":-1},{\"duration\":12}],\"colorFrame\":[{\"tweenEasing\":0},{\"tweenEasing\":0,\"value\":{\"aM\":0}},{\"duration\":3,\"tweenEasing\":0},{\"tweenEasing\":0},{\"duration\":7,\"value\":{\"aM\":0}}]},{\"name\":\"图层 4\",\"displayFrame\":[{\"value\":-1},{\"duration\":12}],\"colorFrame\":[{\"tweenEasing\":0},{\"tweenEasing\":0,\"value\":{\"aM\":0}},{\"duration\":3,\"tweenEasing\":0},{\"tweenEasing\":0},{\"duration\":7,\"value\":{\"aM\":0}}]},{\"name\":\"图层 5\",\"displayFrame\":[{\"value\":-1},{\"duration\":12}],\"colorFrame\":[{\"tweenEasing\":0},{\"tweenEasing\":0,\"value\":{\"aM\":0}},{\"duration\":3,\"tweenEasing\":0},{\"tweenEasing\":0},{\"duration\":7,\"value\":{\"aM\":0}}]},{\"name\":\"图层 6\",\"displayFrame\":[{\"value\":-1},{\"duration\":12}],\"colorFrame\":[{\"tweenEasing\":0},{\"tweenEasing\":0,\"value\":{\"aM\":0}},{\"duration\":3,\"tweenEasing\":0},{\"tweenEasing\":0},{\"duration\":7,\"value\":{\"aM\":0}}]},{\"name\":\"图层 7\",\"displayFrame\":[{\"value\":-1},{\"duration\":5},{\"value\":1},{\"duration\":2},{\"duration\":2,\"value\":1},{\"duration\":2}],\"colorFrame\":[{\"tweenEasing\":0},{\"tweenEasing\":0,\"value\":{\"aM\":0}},{\"duration\":5,\"tweenEasing\":0},{\"tweenEasing\":0},{\"tweenEasing\":0,\"value\":{\"aM\":60}},{\"duration\":2,\"tweenEasing\":0,\"value\":{\"aM\":30}},{\"duration\":2,\"tweenEasing\":0,\"value\":{\"aM\":10}},{\"duration\":0,\"value\":{\"aM\":0}}]}]}],\"defaultActions\":[{\"gotoAndPlay\":\"start\"}]}]}"
        ]
      ],
      0,
      0,
      [],
      [],
      []
    ]
  ]
]